kivy_garden/zbarcam/__init__.py
kivy_garden/zbarcam/utils.py
kivy_garden/zbarcam/version.py
kivy_garden/zbarcam/zbarcam.kv
kivy_garden/zbarcam/zbarcam.py
kivy_garden.zbarcam-2020.524.dist-info/LICENSE
kivy_garden.zbarcam-2020.524.dist-info/METADATA
kivy_garden.zbarcam-2020.524.dist-info/WHEEL
kivy_garden.zbarcam-2020.524.dist-info/top_level.txt
kivy_garden.zbarcam-2020.524.dist-info/RECORD
